robotide/__init__.py
robotide/__main__.py
robotide/robotapi.py
robotide/version.py
robotide/action/__init__.py
robotide/action/action.py
robotide/action/actioninfo.py
robotide/action/shortcut.py
robotide/application/CHANGELOG.html
robotide/application/__init__.py
robotide/application/application.py
robotide/application/debugconsole.py
robotide/application/docbook-xsl.css
robotide/application/editorprovider.py
robotide/application/pluginconnector.py
robotide/application/pluginloader.py
robotide/application/releasenotes.py
robotide/application/restartutil.py
robotide/application/updatenotifier.py
robotide/context/__init__.py
robotide/context/coreplugins.py
robotide/context/logger.py
robotide/contrib/__init__.py
robotide/contrib/testrunner/ArgsParser.py
robotide/contrib/testrunner/Command.py
robotide/contrib/testrunner/CommandArgs.py
robotide/contrib/testrunner/FileWriter.py
robotide/contrib/testrunner/Process.py
robotide/contrib/testrunner/SettingsParser.py
robotide/contrib/testrunner/TestRunnerAgent.py
robotide/contrib/testrunner/__init__.py
robotide/contrib/testrunner/runprofiles.py
robotide/contrib/testrunner/testrunner.py
robotide/contrib/testrunner/testrunnerplugin.py
robotide/contrib/testrunner/usages.py
robotide/controller/__init__.py
robotide/controller/arguments.py
robotide/controller/basecontroller.py
robotide/controller/cellinfo.py
robotide/controller/ctrlcommands.py
robotide/controller/dataloader.py
robotide/controller/filecontrollers.py
robotide/controller/macrocontrollers.py
robotide/controller/project.py
robotide/controller/robotdata.py
robotide/controller/settingcontrollers.py
robotide/controller/stepcontrollers.py
robotide/controller/tablecontrollers.py
robotide/controller/tags.py
robotide/controller/testexecutionresults.py
robotide/controller/validators.py
robotide/controller/ui/__init__.py
robotide/controller/ui/treecontroller.py
robotide/editor/__init__.py
robotide/editor/cellrenderer.py
robotide/editor/clipboard.py
robotframework_ride-2.2.2.dist-info/METADATA
robotframework_ride-2.2.2.dist-info/WHEEL
robotframework_ride-2.2.2.dist-info/entry_points.txt
robotframework_ride-2.2.2.dist-info/licenses/LICENSE.txt
robotframework_ride-2.2.2.dist-info/RECORD
